justplot_qt-0.2.0.data/scripts/justplot
libjustplot/__init__.py
libjustplot/color_picker.py
libjustplot/exception.py
libjustplot/main.py
libjustplot/main_window.py
libjustplot/model.py
libjustplot/tree_model.py
libjustplot/ui/main.ui
justplot_qt-0.2.0.dist-info/LICENSE
justplot_qt-0.2.0.dist-info/METADATA
justplot_qt-0.2.0.dist-info/WHEEL
justplot_qt-0.2.0.dist-info/top_level.txt
justplot_qt-0.2.0.dist-info/RECORD
