Metadata-Version: 2.1
Name: justplot-qt
Version: 0.2.0
Summary: Simplt data plotter with GUI
Home-page: https://github.com/Garrus007/justplot
Author: Markov Alex
Author-email: markovalex95@gmail.com
License: MIT
Classifier: License :: OSI Approved :: MIT License
Classifier: Environment :: X11 Applications :: Qt
Classifier: Intended Audience :: Science/Research
Classifier: Topic :: Scientific/Engineering :: Visualization
Classifier: Natural Language :: English
Classifier: Operating System :: POSIX :: Linux
Classifier: Programming Language :: Python :: 3.6
Classifier: Development Status :: 5 - Production/Stable
Requires-Python: >=3.6
License-File: LICENSE
Requires-Dist: PyQt5
Requires-Dist: pyqtgraph
Requires-Dist: pandas
